{"updatedTime":"Cập nhật ngày: 29/10/2024 09:11","items":[{"goldType":"Vàng miếng SJC 999.9","priceBuy":"8,700","priceSell":"8,900"},{"goldType":"Nhẫn Trơn PNJ 999.9","priceBuy":"8,780","priceSell":"8,890"},{"goldType":"Vàng Kim Bảo 999.9","priceBuy":"8,780","priceSell":"8,890"},{"goldType":"Vàng Phúc Lộc Tài 999.9","priceBuy":"8,780","priceSell":"8,890"},{"goldType":"Vàng nữ trang 999.9","priceBuy":"8,770","priceSell":"8,850"},{"goldType":"Vàng nữ trang 999","priceBuy":"8,761","priceSell":"8,841"},{"goldType":"Vàng nữ trang 99","priceBuy":"8,672","priceSell":"8,772"},{"goldType":"Vàng 750 (18K)","priceBuy":"6,513","priceSell":"6,653"},{"goldType":"Vàng 585 (14K)","priceBuy":"5,052","priceSell":"5,192"},{"goldType":"Vàng 416 (10K)","priceBuy":"3,557","priceSell":"3,697"},{"goldType":"Vàng PNJ - Phượng Hoàng","priceBuy":"8,780","priceSell":"8,890"},{"goldType":"Vàng 916 (22K)","priceBuy":"8,067","priceSell":"8,117"},{"goldType":"Vàng 650 (15.6K)","priceBuy":"5,628","priceSell":"5,768"},{"goldType":"Vàng 680 (16.3K)","priceBuy":"5,893","priceSell":"6,033"},{"goldType":"Vàng 610 (14.6K)","priceBuy":"5,274","priceSell":"5,414"},{"goldType":"Vàng 375 (9K)","priceBuy":"3,194","priceSell":"3,334"},{"goldType":"Vàng 333 (8K)","priceBuy":"2,796","priceSell":"2,936"}]}